{"v":"5.6.5","fr":24,"ip":0,"op":15,"w":280,"h":600,"nm":"game_ghostfestival_censer","ddd":0,"assets":[],"layers":[{"ddd":0,"ind":1,"ty":4,"nm":"censer Outlines","sr":1,"ks":{"o":{"a":0,"k":100,"ix":11},"r":{"a":0,"k":0,"ix":10},"p":{"a":0,"k":[140,300,0],"ix":2},"a":{"a":0,"k":[140,300,0],"ix":1},"s":{"a":0,"k":[100,100,100],"ix":6}},"ao":0,"shapes":[{"ty":"gr","it":[{"ind":0,"ty":"sh","ix":1,"ks":{"a":0,"k":{"i":[[0,0],[0,0],[0,0],[0,0]],"o":[[0,0],[0,0],[0,0],[0,0]],"v":[[-139.857,3.022],[139.857,3.022],[139.857,-3.021],[-139.857,-3.021]],"c":true},"ix":2},"nm":"Path 1","mn":"ADBE Vector Shape - Group","hd":false},{"ty":"fl","c":{"a":0,"k":[1,0.808000033509,0.395999983245,1],"ix":4},"o":{"a":0,"k":100,"ix":5},"r":1,"bm":0,"nm":"Fill 1","mn":"ADBE Vector Graphic - Fill","hd":false},{"ty":"tr","p":{"a":0,"k":[139.883,337.695],"ix":2},"a":{"a":0,"k":[0,0],"ix":1},"s":{"a":0,"k":[100,100],"ix":3},"r":{"a":0,"k":0,"ix":6},"o":{"a":0,"k":100,"ix":7},"sk":{"a":0,"k":0,"ix":4},"sa":{"a":0,"k":0,"ix":5},"nm":"Transform"}],"nm":"Group 1","np":2,"cix":2,"bm":0,"ix":1,"mn":"ADBE Vector Group","hd":false},{"ty":"gr","it":[{"ind":0,"ty":"sh","ix":1,"ks":{"a":0,"k":{"i":[[0,0],[0,0],[0,0],[0,0]],"o":[[0,0],[0,0],[0,0],[0,0]],"v":[[-139.857,3.022],[139.857,3.022],[139.857,-3.021],[-139.857,-3.021]],"c":true},"ix":2},"nm":"Path 1","mn":"ADBE Vector Shape - Group","hd":false},{"ty":"fl","c":{"a":0,"k":[1,0.808000033509,0.395999983245,1],"ix":4},"o":{"a":0,"k":100,"ix":5},"r":1,"bm":0,"nm":"Fill 1","mn":"ADBE Vector Graphic - Fill","hd":false},{"ty":"tr","p":{"a":0,"k":[139.883,301.438],"ix":2},"a":{"a":0,"k":[0,0],"ix":1},"s":{"a":0,"k":[100,100],"ix":3},"r":{"a":0,"k":0,"ix":6},"o":{"a":0,"k":100,"ix":7},"sk":{"a":0,"k":0,"ix":4},"sa":{"a":0,"k":0,"ix":5},"nm":"Transform"}],"nm":"Group 2","np":2,"cix":2,"bm":0,"ix":2,"mn":"ADBE Vector Group","hd":false},{"ty":"gr","it":[{"ind":0,"ty":"sh","ix":1,"ks":{"a":0,"k":{"i":[[0,0],[1.668,0],[0,0],[0,-1.668],[0,0],[-1.669,0],[0,0],[0,0],[0,0],[0,0],[0,0],[0,0],[-1.669,0],[0,0],[0,1.668],[0,0],[1.669,0],[0,0],[0,0],[0,0],[0,0],[0,0]],"o":[[0,-1.669],[0,0],[-1.669,0],[0,0],[0,1.669],[0,0],[0,0],[0,0],[0,0],[0,0],[0,0],[0,1.669],[0,0],[1.669,0],[0,0],[-0.001,-1.669],[0,0],[0,0],[0,0],[0,0],[0,0],[0,0]],"v":[[3.021,-6.043],[0.001,-9.064],[-12.085,-9.064],[-15.107,-6.043],[-15.107,6.043],[-12.085,9.064],[-6.042,9.064],[-6.042,3.021],[-9.064,3.021],[-9.064,-3.022],[-3.021,-3.022],[-3.021,6.043],[0.001,9.064],[12.085,9.064],[15.107,6.043],[15.107,-6.043],[12.085,-9.064],[6.042,-9.064],[6.042,-3.022],[9.064,-3.022],[9.064,3.021],[3.021,3.021]],"c":true},"ix":2},"nm":"Path 1","mn":"ADBE Vector Shape - Group","hd":false},{"ty":"fl","c":{"a":0,"k":[1,0.808000033509,0.395999983245,1],"ix":4},"o":{"a":0,"k":100,"ix":5},"r":1,"bm":0,"nm":"Fill 1","mn":"ADBE Vector Graphic - Fill","hd":false},{"ty":"tr","p":{"a":0,"k":[15.133,319.565],"ix":2},"a":{"a":0,"k":[0,0],"ix":1},"s":{"a":0,"k":[100,100],"ix":3},"r":{"a":0,"k":0,"ix":6},"o":{"a":0,"k":100,"ix":7},"sk":{"a":0,"k":0,"ix":4},"sa":{"a":0,"k":0,"ix":5},"nm":"Transform"}],"nm":"Group 3","np":2,"cix":2,"bm":0,"ix":3,"mn":"ADBE Vector Group","hd":false},{"ty":"gr","it":[{"ind":0,"ty":"sh","ix":1,"ks":{"a":0,"k":{"i":[[0,0],[1.668,0],[0,0],[0,0],[0,-1.668],[0,0],[-1.669,0],[0,0],[0,0],[0,0],[0,0],[0,0],[0,0],[-1.669,0],[0,0],[0,1.668],[0,0],[1.669,0],[0,0],[0,0],[0,0],[0,0],[0,0]],"o":[[0,-1.669],[0,0],[0,0],[-1.668,0],[0,0],[0,1.669],[0,0],[0,0],[0,0],[0,0],[0,0],[0,0],[0,1.669],[0,0],[1.669,0],[0,0],[0,-1.669],[0,0],[0,0],[0,0],[0,0],[0,0],[0,0]],"v":[[3.022,-6.043],[0.001,-9.064],[-12.085,-9.064],[-12.086,-9.064],[-15.107,-6.043],[-15.107,6.043],[-12.085,9.064],[-6.042,9.064],[-6.042,3.021],[-9.064,3.021],[-9.064,-3.022],[-3.021,-3.022],[-3.021,6.043],[0.001,9.064],[12.086,9.064],[15.107,6.043],[15.107,-6.043],[12.086,-9.064],[6.043,-9.064],[6.043,-3.022],[9.065,-3.022],[9.065,3.021],[3.022,3.021]],"c":true},"ix":2},"nm":"Path 1","mn":"ADBE Vector Shape - Group","hd":false},{"ty":"fl","c":{"a":0,"k":[1,0.808000033509,0.395999983245,1],"ix":4},"o":{"a":0,"k":100,"ix":5},"r":1,"bm":0,"nm":"Fill 1","mn":"ADBE Vector Graphic - Fill","hd":false},{"ty":"tr","p":{"a":0,"k":[50.195,319.565],"ix":2},"a":{"a":0,"k":[0,0],"ix":1},"s":{"a":0,"k":[100,100],"ix":3},"r":{"a":0,"k":0,"ix":6},"o":{"a":0,"k":100,"ix":7},"sk":{"a":0,"k":0,"ix":4},"sa":{"a":0,"k":0,"ix":5},"nm":"Transform"}],"nm":"Group 4","np":2,"cix":2,"bm":0,"ix":4,"mn":"ADBE Vector Group","hd":false},{"ty":"gr","it":[{"ind":0,"ty":"sh","ix":1,"ks":{"a":0,"k":{"i":[[0,0],[1.668,0],[0,0],[0,0],[0,-1.668],[0,0],[-1.669,0],[0,0],[0,0],[0,0],[0,0],[0,0],[0,0],[-1.669,0],[0,0],[0,1.668],[0,0],[1.669,0],[0,0],[0,0],[0,0],[0,0],[0,0]],"o":[[0,-1.669],[0,0],[0,0],[-1.668,0],[0,0],[0,1.669],[0,0],[0,0],[0,0],[0,0],[0,0],[0,0],[0,1.669],[0,0],[1.669,0],[0,0],[0,-1.669],[0,0],[0,0],[0,0],[0,0],[0,0],[0,0]],"v":[[3.022,-6.043],[0.001,-9.064],[-12.085,-9.064],[-12.086,-9.064],[-15.107,-6.043],[-15.107,6.043],[-12.085,9.064],[-6.042,9.064],[-6.042,3.021],[-9.064,3.021],[-9.064,-3.022],[-3.021,-3.022],[-3.021,6.043],[0.001,9.064],[12.086,9.064],[15.107,6.043],[15.107,-6.043],[12.086,-9.064],[6.043,-9.064],[6.043,-3.022],[9.064,-3.022],[9.064,3.021],[3.022,3.021]],"c":true},"ix":2},"nm":"Path 1","mn":"ADBE Vector Shape - Group","hd":false},{"ty":"fl","c":{"a":0,"k":[1,0.808000033509,0.395999983245,1],"ix":4},"o":{"a":0,"k":100,"ix":5},"r":1,"bm":0,"nm":"Fill 1","mn":"ADBE Vector Graphic - Fill","hd":false},{"ty":"tr","p":{"a":0,"k":[85.258,319.565],"ix":2},"a":{"a":0,"k":[0,0],"ix":1},"s":{"a":0,"k":[100,100],"ix":3},"r":{"a":0,"k":0,"ix":6},"o":{"a":0,"k":100,"ix":7},"sk":{"a":0,"k":0,"ix":4},"sa":{"a":0,"k":0,"ix":5},"nm":"Transform"}],"nm":"Group 5","np":2,"cix":2,"bm":0,"ix":5,"mn":"ADBE Vector Group","hd":false},{"ty":"gr","it":[{"ind":0,"ty":"sh","ix":1,"ks":{"a":0,"k":{"i":[[0,0],[1.668,0],[0,0],[0,-1.668],[0,0],[-1.669,0],[0,0],[0,0],[0,0],[0,0],[0,0],[0,0],[-1.669,0],[0,0],[0,0],[0,1.668],[0,0],[1.669,0],[0,0],[0,0],[0,0],[0,0],[0,0]],"o":[[0,-1.669],[0,0],[-1.669,0],[0,0],[0,1.669],[0,0],[0,0],[0,0],[0,0],[0,0],[0,0],[0.001,1.669],[0,0],[0,0],[1.668,0],[0,0],[0,-1.669],[0,0],[0,0],[0,0],[0,0],[0,0],[0,0]],"v":[[3.021,-6.043],[0,-9.064],[-12.086,-9.064],[-15.107,-6.043],[-15.107,6.043],[-12.086,9.064],[-6.043,9.064],[-6.043,3.021],[-9.064,3.021],[-9.064,-3.022],[-3.022,-3.022],[-3.022,6.043],[0,9.064],[12.085,9.064],[12.086,9.064],[15.107,6.043],[15.107,-6.043],[12.085,-9.064],[6.042,-9.064],[6.042,-3.022],[9.064,-3.022],[9.064,3.021],[3.021,3.021]],"c":true},"ix":2},"nm":"Path 1","mn":"ADBE Vector Shape - Group","hd":false},{"ty":"fl","c":{"a":0,"k":[1,0.808000033509,0.395999983245,1],"ix":4},"o":{"a":0,"k":100,"ix":5},"r":1,"bm":0,"nm":"Fill 1","mn":"ADBE Vector Graphic - Fill","hd":false},{"ty":"tr","p":{"a":0,"k":[120.321,319.565],"ix":2},"a":{"a":0,"k":[0,0],"ix":1},"s":{"a":0,"k":[100,100],"ix":3},"r":{"a":0,"k":0,"ix":6},"o":{"a":0,"k":100,"ix":7},"sk":{"a":0,"k":0,"ix":4},"sa":{"a":0,"k":0,"ix":5},"nm":"Transform"}],"nm":"Group 6","np":2,"cix":2,"bm":0,"ix":6,"mn":"ADBE Vector Group","hd":false},{"ty":"gr","it":[{"ind":0,"ty":"sh","ix":1,"ks":{"a":0,"k":{"i":[[0,0],[1.668,0],[0,0],[0,-1.668],[0,0],[-1.668,0],[0,0],[0,0],[0,0],[0,0],[0,0],[0,0],[-1.669,0],[0,0],[0,1.668],[0,0],[1.669,0],[0,0],[0,0],[0,0],[0,0],[0,0]],"o":[[0,-1.669],[0,0],[-1.669,0],[0,0],[0,1.669],[0,0],[0,0],[0,0],[0,0],[0,0],[0,0],[0,1.669],[0,0],[1.669,0],[0,0],[0,-1.669],[0,0],[0,0],[0,0],[0,0],[0,0],[0,0]],"v":[[3.021,-6.043],[0,-9.064],[-12.086,-9.064],[-15.107,-6.043],[-15.107,6.043],[-12.086,9.064],[-6.043,9.064],[-6.043,3.021],[-9.065,3.021],[-9.065,-3.022],[-3.022,-3.022],[-3.022,6.043],[0,9.064],[12.085,9.064],[15.107,6.043],[15.107,-6.043],[12.085,-9.064],[6.042,-9.064],[6.042,-3.022],[9.064,-3.022],[9.064,3.021],[3.021,3.021]],"c":true},"ix":2},"nm":"Path 1","mn":"ADBE Vector Shape - Group","hd":false},{"ty":"fl","c":{"a":0,"k":[1,0.808000033509,0.395999983245,1],"ix":4},"o":{"a":0,"k":100,"ix":5},"r":1,"bm":0,"nm":"Fill 1","mn":"ADBE Vector Graphic - Fill","hd":false},{"ty":"tr","p":{"a":0,"k":[155.383,319.565],"ix":2},"a":{"a":0,"k":[0,0],"ix":1},"s":{"a":0,"k":[100,100],"ix":3},"r":{"a":0,"k":0,"ix":6},"o":{"a":0,"k":100,"ix":7},"sk":{"a":0,"k":0,"ix":4},"sa":{"a":0,"k":0,"ix":5},"nm":"Transform"}],"nm":"Group 7","np":2,"cix":2,"bm":0,"ix":7,"mn":"ADBE Vector Group","hd":false},{"ty":"gr","it":[{"ind":0,"ty":"sh","ix":1,"ks":{"a":0,"k":{"i":[[0,0],[1.668,0],[0,0],[0,-1.668],[0,0],[-1.669,0],[0,0],[0,0],[0,0],[0,0],[0,0],[0,0],[-1.669,0],[0,0],[0,1.668],[0,0],[1.669,0],[0,0],[0,0],[0,0],[0,0],[0,0]],"o":[[0,-1.669],[0,0],[-1.669,0],[0,0],[0,1.669],[0,0],[0,0],[0,0],[0,0],[0,0],[0,0],[0,1.669],[0,0],[1.669,0],[0,0],[0,-1.669],[0,0],[0,0],[0,0],[0,0],[0,0],[0,0]],"v":[[3.022,-6.043],[0.001,-9.064],[-12.085,-9.064],[-15.107,-6.043],[-15.107,6.043],[-12.085,9.064],[-6.042,9.064],[-6.042,3.021],[-9.064,3.021],[-9.064,-3.022],[-3.021,-3.022],[-3.021,6.043],[0.001,9.064],[12.086,9.064],[15.108,6.043],[15.108,-6.043],[12.086,-9.064],[6.043,-9.064],[6.043,-3.022],[9.065,-3.022],[9.065,3.021],[3.022,3.021]],"c":true},"ix":2},"nm":"Path 1","mn":"ADBE Vector Shape - Group","hd":false},{"ty":"fl","c":{"a":0,"k":[1,0.808000033509,0.395999983245,1],"ix":4},"o":{"a":0,"k":100,"ix":5},"r":1,"bm":0,"nm":"Fill 1","mn":"ADBE Vector Graphic - Fill","hd":false},{"ty":"tr","p":{"a":0,"k":[190.445,319.565],"ix":2},"a":{"a":0,"k":[0,0],"ix":1},"s":{"a":0,"k":[100,100],"ix":3},"r":{"a":0,"k":0,"ix":6},"o":{"a":0,"k":100,"ix":7},"sk":{"a":0,"k":0,"ix":4},"sa":{"a":0,"k":0,"ix":5},"nm":"Transform"}],"nm":"Group 8","np":2,"cix":2,"bm":0,"ix":8,"mn":"ADBE Vector Group","hd":false},{"ty":"gr","it":[{"ind":0,"ty":"sh","ix":1,"ks":{"a":0,"k":{"i":[[0,0],[1.668,0],[0,0],[0,-1.668],[0,0],[-1.669,0],[0,0],[0,0],[0,0],[0,0],[0,0],[0,0],[-1.669,0],[0,0],[0,1.668],[0,0],[1.669,0],[0,0],[0,0],[0,0],[0,0],[0,0]],"o":[[0,-1.669],[0,0],[-1.669,0],[0,0],[0,1.669],[0,0],[0,0],[0,0],[0,0],[0,0],[0,0],[0,1.669],[0,0],[1.669,0],[0,0],[0,-1.669],[0,0],[0,0],[0,0],[0,0],[0,0],[0,0]],"v":[[3.022,-6.043],[0.001,-9.064],[-12.085,-9.064],[-15.107,-6.043],[-15.107,6.043],[-12.085,9.064],[-6.042,9.064],[-6.042,3.021],[-9.064,3.021],[-9.064,-3.022],[-3.021,-3.022],[-3.021,6.043],[0.001,9.064],[12.086,9.064],[15.108,6.043],[15.108,-6.043],[12.086,-9.064],[6.043,-9.064],[6.043,-3.022],[9.065,-3.022],[9.065,3.021],[3.022,3.021]],"c":true},"ix":2},"nm":"Path 1","mn":"ADBE Vector Shape - Group","hd":false},{"ty":"fl","c":{"a":0,"k":[1,0.808000033509,0.395999983245,1],"ix":4},"o":{"a":0,"k":100,"ix":5},"r":1,"bm":0,"nm":"Fill 1","mn":"ADBE Vector Graphic - Fill","hd":false},{"ty":"tr","p":{"a":0,"k":[225.508,319.565],"ix":2},"a":{"a":0,"k":[0,0],"ix":1},"s":{"a":0,"k":[100,100],"ix":3},"r":{"a":0,"k":0,"ix":6},"o":{"a":0,"k":100,"ix":7},"sk":{"a":0,"k":0,"ix":4},"sa":{"a":0,"k":0,"ix":5},"nm":"Transform"}],"nm":"Group 9","np":2,"cix":2,"bm":0,"ix":9,"mn":"ADBE Vector Group","hd":false},{"ty":"gr","it":[{"ind":0,"ty":"sh","ix":1,"ks":{"a":0,"k":{"i":[[0,0],[1.668,0],[0,0],[0,-1.668],[0,0],[-1.669,0],[0,0],[0,0],[0,0],[0,0],[0,0],[0,0],[-1.669,0],[0,0],[0,1.668],[0,0],[1.668,0],[0,0],[0,0],[0,0],[0,0],[0,0]],"o":[[0,-1.669],[0,0],[-1.669,0],[0,0],[0,1.669],[0,0],[0,0],[0,0],[0,0],[0,0],[0,0],[0,1.669],[0,0],[1.669,0],[0,0],[0,-1.669],[0,0],[0,0],[0,0],[0,0],[0,0],[0,0]],"v":[[3.022,-6.043],[0,-9.064],[-12.085,-9.064],[-15.107,-6.043],[-15.107,6.043],[-12.085,9.064],[-6.042,9.064],[-6.042,3.021],[-9.064,3.021],[-9.064,-3.022],[-3.022,-3.022],[-3.022,6.043],[0,9.064],[12.086,9.064],[15.108,6.043],[15.108,-6.043],[12.086,-9.064],[6.043,-9.064],[6.043,-3.022],[9.065,-3.022],[9.065,3.021],[3.022,3.021]],"c":true},"ix":2},"nm":"Path 1","mn":"ADBE Vector Shape - Group","hd":false},{"ty":"fl","c":{"a":0,"k":[1,0.808000033509,0.395999983245,1],"ix":4},"o":{"a":0,"k":100,"ix":5},"r":1,"bm":0,"nm":"Fill 1","mn":"ADBE Vector Graphic - Fill","hd":false},{"ty":"tr","p":{"a":0,"k":[260.57,319.565],"ix":2},"a":{"a":0,"k":[0,0],"ix":1},"s":{"a":0,"k":[100,100],"ix":3},"r":{"a":0,"k":0,"ix":6},"o":{"a":0,"k":100,"ix":7},"sk":{"a":0,"k":0,"ix":4},"sa":{"a":0,"k":0,"ix":5},"nm":"Transform"}],"nm":"Group 10","np":2,"cix":2,"bm":0,"ix":10,"mn":"ADBE Vector Group","hd":false},{"ty":"gr","it":[{"ind":0,"ty":"sh","ix":1,"ks":{"a":0,"k":{"i":[[0,-0.548],[0,0],[38.525,-11.267],[9.064,0],[0,0],[0,0],[0,0]],"o":[[0,0],[0,42.166],[-8.28,2.427],[0,0],[0,0],[0,0],[0.539,0]],"v":[[55.12,-62.85],[55.12,-1.872],[-11.555,87.168],[-37.649,90.896],[-55.12,90.896],[-55.12,-90.896],[54.141,-90.896]],"c":true},"ix":2},"nm":"Path 1","mn":"ADBE Vector Shape - Group","hd":false},{"ty":"fl","c":{"a":0,"k":[0.783999992819,0.216000007181,0.258999992819,1],"ix":4},"o":{"a":0,"k":100,"ix":5},"r":1,"bm":0,"nm":"Fill 1","mn":"ADBE Vector Graphic - Fill","hd":false},{"ty":"tr","p":{"a":0,"k":[224.88,389.289],"ix":2},"a":{"a":0,"k":[0,0],"ix":1},"s":{"a":0,"k":[100,100],"ix":3},"r":{"a":0,"k":0,"ix":6},"o":{"a":0,"k":100,"ix":7},"sk":{"a":0,"k":0,"ix":4},"sa":{"a":0,"k":0,"ix":5},"nm":"Transform"}],"nm":"Group 11","np":2,"cix":2,"bm":0,"ix":11,"mn":"ADBE Vector Group","hd":false},{"ty":"gr","it":[{"ind":0,"ty":"sh","ix":1,"ks":{"a":0,"k":{"i":[[0,0],[0,0],[0,0],[8.28,2.427],[0,42.166],[0,0],[-0.538,0]],"o":[[0,0],[0,0],[-9.063,0],[-38.525,-11.267],[0,0],[0,-0.548],[0,0]],"v":[[84.88,-90.896],[84.88,90.896],[7.889,90.896],[-18.205,87.168],[-84.88,-1.872],[-84.88,-62.85],[-83.901,-90.896]],"c":true},"ix":2},"nm":"Path 1","mn":"ADBE Vector Shape - Group","hd":false},{"ty":"fl","c":{"a":0,"k":[0.925,0.277999997606,0.277999997606,1],"ix":4},"o":{"a":0,"k":100,"ix":5},"r":1,"bm":0,"nm":"Fill 1","mn":"ADBE Vector Graphic - Fill","hd":false},{"ty":"tr","p":{"a":0,"k":[84.88,389.289],"ix":2},"a":{"a":0,"k":[0,0],"ix":1},"s":{"a":0,"k":[100,100],"ix":3},"r":{"a":0,"k":0,"ix":6},"o":{"a":0,"k":100,"ix":7},"sk":{"a":0,"k":0,"ix":4},"sa":{"a":0,"k":0,"ix":5},"nm":"Transform"}],"nm":"Group 12","np":4,"cix":2,"bm":0,"ix":12,"mn":"ADBE Vector Group","hd":false},{"ty":"gr","it":[{"ind":0,"ty":"sh","ix":1,"ks":{"a":0,"k":{"i":[[-8.28,2.427],[23.51,-7.292],[0,0],[0,0]],"o":[[-2.506,25.232],[0,0],[0,0],[9.064,0]],"v":[[21.783,-26.666],[-21.783,26.667],[-21.783,-22.937],[-4.312,-22.937]],"c":true},"ix":2},"nm":"Path 1","mn":"ADBE Vector Shape - Group","hd":false},{"ty":"fl","c":{"a":0,"k":[0.596000043084,0.125,0.165000002992,1],"ix":4},"o":{"a":0,"k":100,"ix":5},"r":1,"bm":0,"nm":"Fill 1","mn":"ADBE Vector Graphic - Fill","hd":false},{"ty":"tr","p":{"a":0,"k":[191.543,503.123],"ix":2},"a":{"a":0,"k":[0,0],"ix":1},"s":{"a":0,"k":[100,100],"ix":3},"r":{"a":0,"k":0,"ix":6},"o":{"a":0,"k":100,"ix":7},"sk":{"a":0,"k":0,"ix":4},"sa":{"a":0,"k":0,"ix":5},"nm":"Transform"}],"nm":"Group 13","np":2,"cix":2,"bm":0,"ix":13,"mn":"ADBE Vector Group","hd":false},{"ty":"gr","it":[{"ind":0,"ty":"sh","ix":1,"ks":{"a":0,"k":{"i":[[0,0],[0,0],[6.44,0],[0,0],[11.286,11.295],[1.459,14.73],[0,2.114]],"o":[[0,0],[-5.844,1.811],[0,0],[-17.226,0],[-9.915,-9.906],[-0.206,-2.056],[0,0]],"v":[[51.699,-31.189],[51.699,28.399],[33.2,31.189],[10.678,31.189],[-33.426,12.915],[-51.386,-24.934],[-51.699,-31.189]],"c":true},"ix":2},"nm":"Path 1","mn":"ADBE Vector Shape - Group","hd":false},{"ty":"fl","c":{"a":0,"k":[0.783999992819,0.216000007181,0.258999992819,1],"ix":4},"o":{"a":0,"k":100,"ix":5},"r":1,"bm":0,"nm":"Fill 1","mn":"ADBE Vector Graphic - Fill","hd":false},{"ty":"tr","p":{"a":0,"k":[118.061,501.391],"ix":2},"a":{"a":0,"k":[0,0],"ix":1},"s":{"a":0,"k":[100,100],"ix":3},"r":{"a":0,"k":0,"ix":6},"o":{"a":0,"k":100,"ix":7},"sk":{"a":0,"k":0,"ix":4},"sa":{"a":0,"k":0,"ix":5},"nm":"Transform"}],"nm":"Group 14","np":2,"cix":2,"bm":0,"ix":14,"mn":"ADBE Vector Group","hd":false},{"ty":"gr","it":[{"ind":0,"ty":"sh","ix":1,"ks":{"a":0,"k":{"i":[[0,-21.64],[74.638,0],[0,21.639],[-74.637,0]],"o":[[0,21.639],[-74.637,0],[0,-21.64],[74.638,0]],"v":[[135.143,0],[-0.001,39.182],[-135.143,0],[-0.001,-39.181]],"c":true},"ix":2},"nm":"Path 1","mn":"ADBE Vector Shape - Group","hd":false},{"ty":"fl","c":{"a":0,"k":[0.925,0.277999997606,0.277999997606,1],"ix":4},"o":{"a":0,"k":100,"ix":5},"r":1,"bm":0,"nm":"Fill 1","mn":"ADBE Vector Graphic - Fill","hd":false},{"ty":"tr","p":{"a":0,"k":[140.003,525.872],"ix":2},"a":{"a":0,"k":[0,0],"ix":1},"s":{"a":0,"k":[100,100],"ix":3},"r":{"a":0,"k":0,"ix":6},"o":{"a":0,"k":100,"ix":7},"sk":{"a":0,"k":0,"ix":4},"sa":{"a":0,"k":0,"ix":5},"nm":"Transform"}],"nm":"Group 15","np":2,"cix":2,"bm":0,"ix":15,"mn":"ADBE Vector Group","hd":false},{"ty":"gr","it":[{"ind":0,"ty":"sh","ix":1,"ks":{"a":0,"k":{"i":[[0,0],[0,0],[98.099,0],[0,21.641],[0,0],[0,0],[-53.983,0],[-21.651,-13.265]],"o":[[0,0],[0,21.641],[-98.099,0],[0,0],[0,0],[21.651,-13.265],[53.984,0],[0,0]],"v":[[135.145,-30.367],[135.145,-3.581],[-0.001,42.757],[-135.145,-3.581],[-135.145,-30.367],[-122.22,-20.323],[-0.001,-42.757],[122.219,-20.323]],"c":true},"ix":2},"nm":"Path 1","mn":"ADBE Vector Shape - Group","hd":false},{"ty":"fl","c":{"a":0,"k":[0.783999992819,0.216000007181,0.258999992819,1],"ix":4},"o":{"a":0,"k":100,"ix":5},"r":1,"bm":0,"nm":"Fill 1","mn":"ADBE Vector Graphic - Fill","hd":false},{"ty":"tr","p":{"a":0,"k":[139.998,556.243],"ix":2},"a":{"a":0,"k":[0,0],"ix":1},"s":{"a":0,"k":[100,100],"ix":3},"r":{"a":0,"k":0,"ix":6},"o":{"a":0,"k":100,"ix":7},"sk":{"a":0,"k":0,"ix":4},"sa":{"a":0,"k":0,"ix":5},"nm":"Transform"}],"nm":"Group 16","np":2,"cix":2,"bm":0,"ix":16,"mn":"ADBE Vector Group","hd":false}],"ip":0,"op":15,"st":0,"bm":0},{"ddd":0,"ind":2,"ty":4,"nm":"incense1 Outlines","sr":1,"ks":{"o":{"a":1,"k":[{"i":{"x":[0.667],"y":[1]},"o":{"x":[0.333],"y":[0]},"t":0,"s":[0]},{"t":2,"s":[100]}],"ix":11},"r":{"a":0,"k":0,"ix":10},"p":{"a":1,"k":[{"i":{"x":0.667,"y":1},"o":{"x":0.333,"y":0},"t":0,"s":[140,183.473,0],"to":[0,21.5,0],"ti":[0,-21.5,0]},{"t":6,"s":[140,312.473,0]}],"ix":2},"a":{"a":0,"k":[140,312.473,0],"ix":1},"s":{"a":0,"k":[100,100,100],"ix":6}},"ao":0,"shapes":[{"ty":"gr","it":[{"ind":0,"ty":"sh","ix":1,"ks":{"a":0,"k":{"i":[[0,0],[0,0],[6.475,0],[0,6.474],[0,0]],"o":[[0,0],[0,6.474],[-6.474,0],[0,0],[0,0]],"v":[[11.723,-20.418],[11.723,8.695],[-0.001,20.418],[-11.723,8.695],[-11.723,-20.418]],"c":true},"ix":2},"nm":"Path 1","mn":"ADBE Vector Shape - Group","hd":false},{"ty":"fl","c":{"a":0,"k":[0.925,0.277999997606,0.277999997606,1],"ix":4},"o":{"a":0,"k":100,"ix":5},"r":1,"bm":0,"nm":"Fill 1","mn":"ADBE Vector Graphic - Fill","hd":false},{"ty":"tr","p":{"a":0,"k":[140,292.056],"ix":2},"a":{"a":0,"k":[0,0],"ix":1},"s":{"a":0,"k":[100,100],"ix":3},"r":{"a":0,"k":0,"ix":6},"o":{"a":0,"k":100,"ix":7},"sk":{"a":0,"k":0,"ix":4},"sa":{"a":0,"k":0,"ix":5},"nm":"Transform"}],"nm":"Group 1","np":2,"cix":2,"bm":0,"ix":1,"mn":"ADBE Vector Group","hd":false},{"ty":"gr","it":[{"ind":0,"ty":"sh","ix":1,"ks":{"a":0,"k":{"i":[[0,-6.471],[0,0],[0,0],[0,0],[-6.471,0]],"o":[[0,0],[0,0],[0,0],[0,-6.471],[6.484,0]],"v":[[11.723,-58.549],[11.723,70.265],[-11.723,70.265],[-11.723,-58.549],[-0.007,-70.265]],"c":true},"ix":2},"nm":"Path 1","mn":"ADBE Vector Shape - Group","hd":false},{"ty":"fl","c":{"a":0,"k":[1,0.808000033509,0.395999983245,1],"ix":4},"o":{"a":0,"k":100,"ix":5},"r":1,"bm":0,"nm":"Fill 1","mn":"ADBE Vector Graphic - Fill","hd":false},{"ty":"tr","p":{"a":0,"k":[140,201.372],"ix":2},"a":{"a":0,"k":[0,0],"ix":1},"s":{"a":0,"k":[100,100],"ix":3},"r":{"a":0,"k":0,"ix":6},"o":{"a":0,"k":100,"ix":7},"sk":{"a":0,"k":0,"ix":4},"sa":{"a":0,"k":0,"ix":5},"nm":"Transform"}],"nm":"Group 2","np":2,"cix":2,"bm":0,"ix":2,"mn":"ADBE Vector Group","hd":false}],"ip":0,"op":15,"st":0,"bm":0},{"ddd":0,"ind":3,"ty":4,"nm":"incense2 Outlines","sr":1,"ks":{"o":{"a":1,"k":[{"i":{"x":[0.667],"y":[1]},"o":{"x":[0.333],"y":[0]},"t":3,"s":[0]},{"t":5,"s":[100]}],"ix":11},"r":{"a":0,"k":0,"ix":10},"p":{"a":1,"k":[{"i":{"x":0.667,"y":1},"o":{"x":0.333,"y":0},"t":3,"s":[95.459,183.473,0],"to":[0,21.5,0],"ti":[0,-21.5,0]},{"t":9,"s":[95.459,312.473,0]}],"ix":2},"a":{"a":0,"k":[95.459,312.473,0],"ix":1},"s":{"a":0,"k":[100,100,100],"ix":6}},"ao":0,"shapes":[{"ty":"gr","it":[{"ind":0,"ty":"sh","ix":1,"ks":{"a":0,"k":{"i":[[0,0],[0,0],[6.475,0],[0,6.474],[0,0]],"o":[[0,0],[0,6.474],[-6.474,0],[0,0],[0,0]],"v":[[11.723,-20.418],[11.723,8.695],[-0.001,20.418],[-11.723,8.695],[-11.723,-20.418]],"c":true},"ix":2},"nm":"Path 1","mn":"ADBE Vector Shape - Group","hd":false},{"ty":"fl","c":{"a":0,"k":[0.925,0.277999997606,0.277999997606,1],"ix":4},"o":{"a":0,"k":100,"ix":5},"r":1,"bm":0,"nm":"Fill 1","mn":"ADBE Vector Graphic - Fill","hd":false},{"ty":"tr","p":{"a":0,"k":[95.459,292.056],"ix":2},"a":{"a":0,"k":[0,0],"ix":1},"s":{"a":0,"k":[100,100],"ix":3},"r":{"a":0,"k":0,"ix":6},"o":{"a":0,"k":100,"ix":7},"sk":{"a":0,"k":0,"ix":4},"sa":{"a":0,"k":0,"ix":5},"nm":"Transform"}],"nm":"Group 1","np":2,"cix":2,"bm":0,"ix":1,"mn":"ADBE Vector Group","hd":false},{"ty":"gr","it":[{"ind":0,"ty":"sh","ix":1,"ks":{"a":0,"k":{"i":[[0,-6.471],[0,0],[0,0],[0,0],[-6.471,0]],"o":[[0,0],[0,0],[0,0],[0,-6.471],[6.484,0]],"v":[[11.723,-58.549],[11.723,70.265],[-11.723,70.265],[-11.723,-58.549],[-0.007,-70.265]],"c":true},"ix":2},"nm":"Path 1","mn":"ADBE Vector Shape - Group","hd":false},{"ty":"fl","c":{"a":0,"k":[1,0.808000033509,0.395999983245,1],"ix":4},"o":{"a":0,"k":100,"ix":5},"r":1,"bm":0,"nm":"Fill 1","mn":"ADBE Vector Graphic - Fill","hd":false},{"ty":"tr","p":{"a":0,"k":[95.459,201.372],"ix":2},"a":{"a":0,"k":[0,0],"ix":1},"s":{"a":0,"k":[100,100],"ix":3},"r":{"a":0,"k":0,"ix":6},"o":{"a":0,"k":100,"ix":7},"sk":{"a":0,"k":0,"ix":4},"sa":{"a":0,"k":0,"ix":5},"nm":"Transform"}],"nm":"Group 2","np":2,"cix":2,"bm":0,"ix":2,"mn":"ADBE Vector Group","hd":false}],"ip":0,"op":15,"st":0,"bm":0},{"ddd":0,"ind":4,"ty":4,"nm":"incense3 Outlines","sr":1,"ks":{"o":{"a":1,"k":[{"i":{"x":[0.667],"y":[1]},"o":{"x":[0.333],"y":[0]},"t":6,"s":[0]},{"t":8,"s":[100]}],"ix":11},"r":{"a":0,"k":0,"ix":10},"p":{"a":1,"k":[{"i":{"x":0.667,"y":1},"o":{"x":0.333,"y":0},"t":6,"s":[184.541,183.473,0],"to":[0,21.5,0],"ti":[0,-21.5,0]},{"t":12,"s":[184.541,312.473,0]}],"ix":2},"a":{"a":0,"k":[184.541,312.473,0],"ix":1},"s":{"a":0,"k":[100,100,100],"ix":6}},"ao":0,"shapes":[{"ty":"gr","it":[{"ind":0,"ty":"sh","ix":1,"ks":{"a":0,"k":{"i":[[0,0],[0,0],[6.475,0],[0,6.474],[0,0]],"o":[[0,0],[0,6.474],[-6.473,0],[0,0],[0,0]],"v":[[11.723,-20.418],[11.723,8.695],[-0.001,20.418],[-11.723,8.695],[-11.723,-20.418]],"c":true},"ix":2},"nm":"Path 1","mn":"ADBE Vector Shape - Group","hd":false},{"ty":"fl","c":{"a":0,"k":[0.925,0.277999997606,0.277999997606,1],"ix":4},"o":{"a":0,"k":100,"ix":5},"r":1,"bm":0,"nm":"Fill 1","mn":"ADBE Vector Graphic - Fill","hd":false},{"ty":"tr","p":{"a":0,"k":[184.541,292.056],"ix":2},"a":{"a":0,"k":[0,0],"ix":1},"s":{"a":0,"k":[100,100],"ix":3},"r":{"a":0,"k":0,"ix":6},"o":{"a":0,"k":100,"ix":7},"sk":{"a":0,"k":0,"ix":4},"sa":{"a":0,"k":0,"ix":5},"nm":"Transform"}],"nm":"Group 1","np":2,"cix":2,"bm":0,"ix":1,"mn":"ADBE Vector Group","hd":false},{"ty":"gr","it":[{"ind":0,"ty":"sh","ix":1,"ks":{"a":0,"k":{"i":[[0,-6.471],[0,0],[0,0],[0,0],[-6.47,0]],"o":[[0,0],[0,0],[0,0],[0,-6.471],[6.484,0]],"v":[[11.723,-58.549],[11.723,70.265],[-11.723,70.265],[-11.723,-58.549],[-0.007,-70.265]],"c":true},"ix":2},"nm":"Path 1","mn":"ADBE Vector Shape - Group","hd":false},{"ty":"fl","c":{"a":0,"k":[1,0.808000033509,0.395999983245,1],"ix":4},"o":{"a":0,"k":100,"ix":5},"r":1,"bm":0,"nm":"Fill 1","mn":"ADBE Vector Graphic - Fill","hd":false},{"ty":"tr","p":{"a":0,"k":[184.541,201.372],"ix":2},"a":{"a":0,"k":[0,0],"ix":1},"s":{"a":0,"k":[100,100],"ix":3},"r":{"a":0,"k":0,"ix":6},"o":{"a":0,"k":100,"ix":7},"sk":{"a":0,"k":0,"ix":4},"sa":{"a":0,"k":0,"ix":5},"nm":"Transform"}],"nm":"Group 2","np":2,"cix":2,"bm":0,"ix":2,"mn":"ADBE Vector Group","hd":false}],"ip":0,"op":15,"st":0,"bm":0}],"markers":[]}